{
"meta":{"test_sets":[],"test_metrics":[],"learn_metrics":[{"best_value":"Min","name":"RMSE"}],"launch_mode":"Train","parameters":"","iteration_count":100,"learn_sets":["learn"],"name":"experiment"},
"iterations":[
{"learn":[12.82338302],"iteration":0,"passed_time":0.002896582437,"remaining_time":0.2867616612},
{"learn":[10.98272411],"iteration":1,"passed_time":0.005466970694,"remaining_time":0.267881564},
{"learn":[9.508071948],"iteration":2,"passed_time":0.009193932256,"remaining_time":0.2972704763},
{"learn":[8.469181327],"iteration":3,"passed_time":0.01209394211,"remaining_time":0.2902546105},
{"learn":[7.729963279],"iteration":4,"passed_time":0.01473353182,"remaining_time":0.2799371046},
{"learn":[7.249539364],"iteration":5,"passed_time":0.01707985522,"remaining_time":0.2675843985},
{"learn":[6.746409548],"iteration":6,"passed_time":0.01956127571,"remaining_time":0.2598855202},
{"learn":[6.39712179],"iteration":7,"passed_time":0.02277070015,"remaining_time":0.2618630517},
{"learn":[6.125679917],"iteration":8,"passed_time":0.02529645263,"remaining_time":0.2557752433},
{"learn":[5.916461264],"iteration":9,"passed_time":0.02804776352,"remaining_time":0.2524298717},
{"learn":[5.733787502],"iteration":10,"passed_time":0.0311448554,"remaining_time":0.2519901937},
{"learn":[5.594454696],"iteration":11,"passed_time":0.03432687778,"remaining_time":0.2517304371},
{"learn":[5.503358945],"iteration":12,"passed_time":0.03786304065,"remaining_time":0.2533911182},
{"learn":[5.422354234],"iteration":13,"passed_time":0.04305304673,"remaining_time":0.2644687156},
{"learn":[5.331114232],"iteration":14,"passed_time":0.04656606919,"remaining_time":0.2638743921},
{"learn":[5.266976713],"iteration":15,"passed_time":0.04971149465,"remaining_time":0.2609853469},
{"learn":[5.213950406],"iteration":16,"passed_time":0.05212701031,"remaining_time":0.2545024621},
{"learn":[5.128178525],"iteration":17,"passed_time":0.05472824759,"remaining_time":0.2493175724},
{"learn":[5.084114409],"iteration":18,"passed_time":0.05816252737,"remaining_time":0.2479560378},
{"learn":[5.046351427],"iteration":19,"passed_time":0.06030235679,"remaining_time":0.2412094272},
{"learn":[5.026056941],"iteration":20,"passed_time":0.06281946173,"remaining_time":0.2363208322},
{"learn":[4.994232667],"iteration":21,"passed_time":0.06547630243,"remaining_time":0.2321432541},
{"learn":[4.967766276],"iteration":22,"passed_time":0.0696139311,"remaining_time":0.2330553345},
{"learn":[4.949397218],"iteration":23,"passed_time":0.07189878851,"remaining_time":0.2276794969},
{"learn":[4.922840055],"iteration":24,"passed_time":0.07457877191,"remaining_time":0.2237363157},
{"learn":[4.912259063],"iteration":25,"passed_time":0.07750805708,"remaining_time":0.2205998548},
{"learn":[4.863470271],"iteration":26,"passed_time":0.07994420165,"remaining_time":0.2161454341},
{"learn":[4.825686221],"iteration":27,"passed_time":0.08326438608,"remaining_time":0.2141084213},
{"learn":[4.789737808],"iteration":28,"passed_time":0.08622452793,"remaining_time":0.2111014305},
{"learn":[4.757794003],"iteration":29,"passed_time":0.08891745159,"remaining_time":0.2074740537},
{"learn":[4.732249967],"iteration":30,"passed_time":0.09152589886,"remaining_time":0.2037189362},
{"learn":[4.709773696],"iteration":31,"passed_time":0.09420183504,"remaining_time":0.2001788995},
{"learn":[4.67912788],"iteration":32,"passed_time":0.09704146089,"remaining_time":0.1970235721},
{"learn":[4.653041868],"iteration":33,"passed_time":0.09992759578,"remaining_time":0.1939770977},
{"learn":[4.630307714],"iteration":34,"passed_time":0.1029136154,"remaining_time":0.1911252858},
{"learn":[4.598210451],"iteration":35,"passed_time":0.1059550027,"remaining_time":0.1883644492},
{"learn":[4.588641365],"iteration":36,"passed_time":0.1093982464,"remaining_time":0.1862726898},
{"learn":[4.57561464],"iteration":37,"passed_time":0.1126020622,"remaining_time":0.1837191541},
{"learn":[4.534305835],"iteration":38,"passed_time":0.1155790143,"remaining_time":0.1807774326},
{"learn":[4.529207413],"iteration":39,"passed_time":0.1188347349,"remaining_time":0.1782521024},
{"learn":[4.508173085],"iteration":40,"passed_time":0.1221448599,"remaining_time":0.1757694326},
{"learn":[4.486884593],"iteration":41,"passed_time":0.124190353,"remaining_time":0.1715009637},
{"learn":[4.461693123],"iteration":42,"passed_time":0.1275015167,"remaining_time":0.1690136384},
{"learn":[4.45796163],"iteration":43,"passed_time":0.1303421751,"remaining_time":0.165890041},
{"learn":[4.451934776],"iteration":44,"passed_time":0.1331969316,"remaining_time":0.1627962498},
{"learn":[4.431872125],"iteration":45,"passed_time":0.1356608334,"remaining_time":0.1592540219},
{"learn":[4.406134568],"iteration":46,"passed_time":0.1380890538,"remaining_time":0.1557174437},
{"learn":[4.403196392],"iteration":47,"passed_time":0.1406130178,"remaining_time":0.1523307693},
{"learn":[4.369025258],"iteration":48,"passed_time":0.1433792619,"remaining_time":0.1492314767},
{"learn":[4.354082752],"iteration":49,"passed_time":0.1460014691,"remaining_time":0.1460014691},
{"learn":[4.351491066],"iteration":50,"passed_time":0.1484598964,"remaining_time":0.1426379397},
{"learn":[4.326388455],"iteration":51,"passed_time":0.1514158925,"remaining_time":0.1397685161},
{"learn":[4.324281468],"iteration":52,"passed_time":0.1537062638,"remaining_time":0.1363055547},
{"learn":[4.287305531],"iteration":53,"passed_time":0.156434358,"remaining_time":0.1332588975},
{"learn":[4.263630114],"iteration":54,"passed_time":0.1592286753,"remaining_time":0.1302780071},
{"learn":[4.240078992],"iteration":55,"passed_time":0.161258931,"remaining_time":0.1267034458},
{"learn":[4.226811785],"iteration":56,"passed_time":0.1637558704,"remaining_time":0.1235351303},
{"learn":[4.208145347],"iteration":57,"passed_time":0.1663934162,"remaining_time":0.1204917841},
{"learn":[4.206446472],"iteration":58,"passed_time":0.1688762846,"remaining_time":0.1173547062},
{"learn":[4.187932468],"iteration":59,"passed_time":0.1719343727,"remaining_time":0.1146229152},
{"learn":[4.148192736],"iteration":60,"passed_time":0.1749091191,"remaining_time":0.1118271417},
{"learn":[4.118379204],"iteration":61,"passed_time":0.1770663506,"remaining_time":0.1085245375},
{"learn":[4.09526836],"iteration":62,"passed_time":0.1792585113,"remaining_time":0.1052788083},
{"learn":[4.086196654],"iteration":63,"passed_time":0.1806583547,"remaining_time":0.1016203245},
{"learn":[4.074887586],"iteration":64,"passed_time":0.1829700154,"remaining_time":0.09852231599},
{"learn":[4.060285575],"iteration":65,"passed_time":0.1852353827,"remaining_time":0.09542428804},
{"learn":[4.030762019],"iteration":66,"passed_time":0.1876796501,"remaining_time":0.09243923064},
{"learn":[4.028360378],"iteration":67,"passed_time":0.1896494516,"remaining_time":0.08924680077},
{"learn":[4.010467233],"iteration":68,"passed_time":0.191703669,"remaining_time":0.08612773534},
{"learn":[4.00899504],"iteration":69,"passed_time":0.193512603,"remaining_time":0.08293397272},
{"learn":[3.981794913],"iteration":70,"passed_time":0.1959966401,"remaining_time":0.08005496567},
{"learn":[3.963960358],"iteration":71,"passed_time":0.1980368183,"remaining_time":0.07701431823},
{"learn":[3.937531768],"iteration":72,"passed_time":0.2002113679,"remaining_time":0.07405077992},
{"learn":[3.895560965],"iteration":73,"passed_time":0.2036031092,"remaining_time":0.07153622756},
{"learn":[3.884260497],"iteration":74,"passed_time":0.2056527094,"remaining_time":0.06855090312},
{"learn":[3.845237483],"iteration":75,"passed_time":0.2076098031,"remaining_time":0.06556099045},
{"learn":[3.830961946],"iteration":76,"passed_time":0.2094149592,"remaining_time":0.06255252027},
{"learn":[3.824940361],"iteration":77,"passed_time":0.2114688984,"remaining_time":0.05964507391},
{"learn":[3.806843297],"iteration":78,"passed_time":0.213389844,"remaining_time":0.05672388258},
{"learn":[3.786351625],"iteration":79,"passed_time":0.2153146926,"remaining_time":0.05382867314},
{"learn":[3.771862044],"iteration":80,"passed_time":0.2177177846,"remaining_time":0.0510696038},
{"learn":[3.757800256],"iteration":81,"passed_time":0.2197507509,"remaining_time":0.04823796972},
{"learn":[3.742347649],"iteration":82,"passed_time":0.2209140548,"remaining_time":0.045247457},
{"learn":[3.72573965],"iteration":83,"passed_time":0.2221525393,"remaining_time":0.04231476939},
{"learn":[3.709437674],"iteration":84,"passed_time":0.223512165,"remaining_time":0.03944332323},
{"learn":[3.708290261],"iteration":85,"passed_time":0.2248113955,"remaining_time":0.03659720393},
{"learn":[3.705444407],"iteration":86,"passed_time":0.2261271008,"remaining_time":0.03378910701},
{"learn":[3.683890137],"iteration":87,"passed_time":0.2273419873,"remaining_time":0.03100118009},
{"learn":[3.668943349],"iteration":88,"passed_time":0.2287639082,"remaining_time":0.0282741909},
{"learn":[3.664710982],"iteration":89,"passed_time":0.230164809,"remaining_time":0.02557386767},
{"learn":[3.62106639],"iteration":90,"passed_time":0.2317566481,"remaining_time":0.02292098717},
{"learn":[3.607473976],"iteration":91,"passed_time":0.2330334727,"remaining_time":0.02026378024},
{"learn":[3.596669223],"iteration":92,"passed_time":0.2345750471,"remaining_time":0.01765618634},
{"learn":[3.593249341],"iteration":93,"passed_time":0.2358337988,"remaining_time":0.0150532212},
{"learn":[3.579147746],"iteration":94,"passed_time":0.2371371483,"remaining_time":0.01248090254},
{"learn":[3.563981735],"iteration":95,"passed_time":0.2384838257,"remaining_time":0.009936826071},
{"learn":[3.560709486],"iteration":96,"passed_time":0.2400834628,"remaining_time":0.007425261735},
{"learn":[3.548801222],"iteration":97,"passed_time":0.2417913169,"remaining_time":0.004934516671},
{"learn":[3.54274885],"iteration":98,"passed_time":0.2428763962,"remaining_time":0.002453296932},
{"learn":[3.532656753],"iteration":99,"passed_time":0.2442414852,"remaining_time":0}
]}